hpss_denoiser/__init__.py
hpss_denoiser/cli.py
hpss_denoiser/py.typed
hpss_denoiser/core/__init__.py
hpss_denoiser/core/config.py
hpss_denoiser/core/envelope.py
hpss_denoiser/core/hpss.py
hpss_denoiser/core/mixer.py
hpss_denoiser/core/pipeline.py
hpss_denoiser/core/spectral.py
hpss_denoiser/utils/__init__.py
hpss_denoiser/utils/audio.py
hpss_denoiser/utils/visualization.py
hpss_voice_denoiser-1.23.1.dist-info/METADATA
hpss_voice_denoiser-1.23.1.dist-info/WHEEL
hpss_voice_denoiser-1.23.1.dist-info/entry_points.txt
hpss_voice_denoiser-1.23.1.dist-info/licenses/LICENSE
hpss_voice_denoiser-1.23.1.dist-info/RECORD
