Metadata-Version: 2.4
Name: hpss-voice-denoiser
Version: 1.23.1
Summary: HPSS-based voice denoiser optimized for ASR preprocessing (STT, diarization, speaker embedding)
Project-URL: Homepage, https://github.com/atomys/hpss-voice-denoiser
Project-URL: Documentation, https://github.com/atomys/hpss-voice-denoiser#readme
Project-URL: Repository, https://github.com/atomys/hpss-voice-denoiser
Project-URL: Issues, https://github.com/atomys/hpss-voice-denoiser/issues
Author-email: Atomys <contact@atomys.fr>
License: MIT
License-File: LICENSE
Keywords: asr,audio,denoising,diarization,hpss,preprocessing,speech,stt,voice,whisper
Classifier: Development Status :: 4 - Beta
Classifier: Intended Audience :: Developers
Classifier: Intended Audience :: Science/Research
Classifier: License :: OSI Approved :: MIT License
Classifier: Operating System :: OS Independent
Classifier: Programming Language :: Python :: 3
Classifier: Programming Language :: Python :: 3.10
Classifier: Programming Language :: Python :: 3.11
Classifier: Programming Language :: Python :: 3.12
Classifier: Topic :: Multimedia :: Sound/Audio :: Analysis
Classifier: Topic :: Multimedia :: Sound/Audio :: Speech
Classifier: Topic :: Scientific/Engineering :: Artificial Intelligence
Requires-Python: >=3.10
Requires-Dist: numpy>=1.24.0
Requires-Dist: scipy>=1.10.0
Provides-Extra: all
Requires-Dist: matplotlib>=3.7.0; extra == 'all'
Requires-Dist: mypy>=1.0.0; extra == 'all'
Requires-Dist: pytest-cov>=4.0.0; extra == 'all'
Requires-Dist: pytest>=7.0.0; extra == 'all'
Requires-Dist: ruff>=0.1.0; extra == 'all'
Provides-Extra: dev
Requires-Dist: mypy>=1.0.0; extra == 'dev'
Requires-Dist: pytest-cov>=4.0.0; extra == 'dev'
Requires-Dist: pytest>=7.0.0; extra == 'dev'
Requires-Dist: ruff>=0.1.0; extra == 'dev'
Provides-Extra: visualization
Requires-Dist: matplotlib>=3.7.0; extra == 'visualization'
